{
  "Development": [
    "java",
    "python",
    "sdk",
    "eclipse",
    "idea",
    "intellij",
    "code",
    "vscode",
    "git",
    "maven",
    "gradle",
    "android",
    "studio",
    "netbeans",
    "jdk",
    "jre",
    "dev",
    "programming",
    "compiler",
    "debugger"
  ],
  "Media": [
    "vlc",
    "player",
    "music",
    "video",
    "media",
    "spotify",
    "itunes",
    "winamp",
    "audacity",
    "photoshop",
    "gimp",
    "multimedia",
    "audio",
    "photo",
    "image",
    "adobe",
    "premiere",
    "after",
    "effects"
  ],
  "Security": [
    "antivirus",
    "firewall",
    "kaspersky",
    "norton",
    "security",
    "defender",
    "malware",
    "scanner",
    "mcafee",
    "avast",
    "bitdefender",
    "virus",
    "protection",
    "safe",
    "guard"
  ],
  "Games": [
    "game",
    "steam",
    "origin",
    "battle",
    "launcher",
    "epic",
    "uplay",
    "gog",
    "gaming",
    "play",
    "entertainment",
    "arcade",
    "puzzle",
    "action",
    "adventure",
    "simulation"
  ],
  "Office": [
    "office",
    "word",
    "excel",
    "powerpoint",
    "pdf",
    "reader",
    "writer",
    "calc",
    "libreoffice",
    "openoffice",
    "document",
    "spreadsheet",
    "presentation",
    "acrobat",
    "notebook",
    "text"
  ],
  "Browser": [
    "chrome",
    "firefox",
    "safari",
    "edge",
    "browser",
    "opera",
    "brave",
    "chromium",
    "mozilla",
    "internet",
    "web",
    "surf",
    "navigator"
  ],
  "System": [
    "driver",
    "system",
    "windows",
    "utility",
    "tool",
    "manager",
    "control",
    "settings",
    "config",
    "admin",
    "service",
    "task",
    "process",
    "registry",
    "cleanup"
  ],
  "Communication": [
    "skype",
    "zoom",
    "teams",
    "discord",
    "slack",
    "telegram",
    "whatsapp",
    "messenger",
    "chat",
    "call",
    "meeting",
    "conference",
    "communication"
  ]
}
